_version.py
openmc_plasma_source/__init__.py
openmc_plasma_source/fuel_types.py
openmc_plasma_source/point_source.py
openmc_plasma_source/ring_source.py
openmc_plasma_source/tokamak_source.py
openmc_plasma_source-0.4.0.dist-info/licenses/LICENSE.txt
openmc_plasma_source-0.4.0.dist-info/METADATA
openmc_plasma_source-0.4.0.dist-info/WHEEL
openmc_plasma_source-0.4.0.dist-info/top_level.txt
openmc_plasma_source-0.4.0.dist-info/RECORD
