Metadata-Version: 2.4
Name: openmc_plasma_source
Version: 0.4.0
Summary: Creates tokamak and fusion point sources for OpenMC
Author: Rémi Delaporte-Mathurin
Project-URL: Homepage, https://github.com/fusion-energy/openmc-plasma-source
Project-URL: Bug Tracker, https://github.com/fusion-energy/openmc-plasma-source/issues
Keywords: python,neutron,fusion,source,openmc,energy,tokamak
Classifier: Programming Language :: Python :: 3
Classifier: License :: OSI Approved :: MIT License
Classifier: Operating System :: OS Independent
Requires-Python: >=3.9
License-File: LICENSE.txt
Requires-Dist: numpy>=1.9
Requires-Dist: matplotlib>=3.2.2
Requires-Dist: NeSST>=1.1.0
Provides-Extra: tests
Requires-Dist: pytest>=5.4.3; extra == "tests"
Requires-Dist: pytest-cov; extra == "tests"
Requires-Dist: hypothesis; extra == "tests"
Requires-Dist: NeSST>=1.1.0; extra == "tests"
Requires-Dist: openmc_source_plotter; extra == "tests"
Dynamic: license-file
